{
	"class" : {
		 },
	"instance" : {
		"descriptionAdmin" : "rs 6/24/2014 22:58",
		"descriptionLocation" : "rs 6/24/2014 22:58",
		"descriptionMcUsername" : "rs 6/24/2014 22:58",
		"descriptionName2" : "rs 6/24/2014 22:59",
		"descriptionPath" : "rs 6/24/2014 23:06",
		"descriptionSid" : "rs 7/1/2014 09:58",
		"descriptionWatching" : "rs 7/1/2014 10:19",
		"descriptionWebsite" : "rs 6/24/2014 23:09",
		"favorites:" : "rs 7/7/2014 16:22",
		"jsonDescription" : "rs 7/7/2014 16:24",
		"jsonKey" : "rs 7/1/2014 09:57",
		"jsonKey:" : "rs 7/7/2014 16:23",
		"location" : "rs 6/24/2014 22:56",
		"location:" : "rs 7/7/2014 16:16",
		"mcUsername" : "rs 6/24/2014 22:56",
		"mcUsername:" : "rs 7/7/2014 16:16",
		"name" : "rs 6/24/2014 22:59",
		"name:" : "rs 7/7/2014 16:16",
		"path" : "rs 6/24/2014 23:05",
		"path:" : "rs 7/7/2014 16:23",
		"website" : "rs 6/24/2014 22:56",
		"website:" : "rs 7/7/2014 16:16" } }
